MANIFEST.in
setup.py
jsbridge/__init__.py
jsbridge/jsobjects.py
jsbridge/network.py
jsbridge.egg-info/PKG-INFO
jsbridge.egg-info/SOURCES.txt
jsbridge.egg-info/dependency_links.txt
jsbridge.egg-info/not-zip-safe
jsbridge.egg-info/top_level.txt
jsbridge/extension/chrome.manifest
jsbridge/extension/install.rdf
jsbridge/extension/META-INF/manifest.mf
jsbridge/extension/META-INF/mozilla.rsa
jsbridge/extension/META-INF/mozilla.sf
jsbridge/extension/components/jsbridge.js
jsbridge/extension/resource/modules/Bridge.jsm
jsbridge/extension/resource/modules/Events.jsm
jsbridge/extension/resource/modules/Log.jsm
jsbridge/extension/resource/modules/NSS.jsm
jsbridge/extension/resource/modules/Server.jsm
jsbridge/extension/resource/modules/Sockets.jsm